nbgrader_unittest/__init__.py
nbgrader_unittest/mock.py
nbgrader_unittest_sebastian_stigler-0.0.3.dist-info/LICENSE
nbgrader_unittest_sebastian_stigler-0.0.3.dist-info/METADATA
nbgrader_unittest_sebastian_stigler-0.0.3.dist-info/WHEEL
nbgrader_unittest_sebastian_stigler-0.0.3.dist-info/top_level.txt
nbgrader_unittest_sebastian_stigler-0.0.3.dist-info/RECORD
