Metadata-Version: 2.1
Name: nbgrader-unittest-sebastian-stigler
Version: 0.0.3
Summary: Drop-in replacement for the unittest module to use them in tests for nbgrader assignments.
Home-page: https://in-stigler.htw-aalen.de/gitea/tools/nbgrader_unittest
Author: Sebastian Stigler
Author-email: sebastian.stigler@hs-aalen.de
License: UNKNOWN
Platform: UNKNOWN
Classifier: Programming Language :: Python :: 3
Classifier: License :: OSI Approved :: MIT License
Classifier: Operating System :: OS Independent
Requires-Python: >=3.6
License-File: LICENSE
